{
  "variants": {
    "facing=down": {
      "model": "create_re:block/crate/creative/single"
    },
    "facing=east": {
      "model": "create_re:block/crate/creative/single"
    },
    "facing=north": {
      "model": "create_re:block/crate/creative/single"
    },
    "facing=south": {
      "model": "create_re:block/crate/creative/single"
    },
    "facing=up": {
      "model": "create_re:block/crate/creative/single"
    },
    "facing=west": {
      "model": "create_re:block/crate/creative/single"
    }
  }
}